echopykits/__init__.py
echopykits/__version__.py
echopykits/core.py
echopykits/code_sandbox/README.md
echopykits/code_sandbox/app/confs/uvicorn_config.json
echopykits/code_sandbox/app/confs/uvicorn_config_file.json
echopykits/demos/__init__.py
echopykits/demos/app_new.zip
echopykits/demos/code_sandbox.zip
echopykits/demos/demo.md
echopykits/demos/node_modules.zip
echopykits/demos/test.py
echopykits/demos/tool_lib.zip
echopykits/docs/echo.md
echopykits10-0.1.0.dist-info/licenses/LICENSE
echopykits10-0.1.0.dist-info/METADATA
echopykits10-0.1.0.dist-info/WHEEL
echopykits10-0.1.0.dist-info/top_level.txt
echopykits10-0.1.0.dist-info/RECORD
